k8s_datamodels/__init__.py
k8s_datamodels/api/__init__.py
k8s_datamodels/api/admissionregistration/__init__.py
k8s_datamodels/api/admissionregistration/v1.py
k8s_datamodels/api/apiserverinternal/__init__.py
k8s_datamodels/api/apiserverinternal/v1alpha1.py
k8s_datamodels/api/apps/__init__.py
k8s_datamodels/api/apps/v1.py
k8s_datamodels/api/authentication/__init__.py
k8s_datamodels/api/authentication/v1.py
k8s_datamodels/api/authorization/__init__.py
k8s_datamodels/api/authorization/v1.py
k8s_datamodels/api/autoscaling/__init__.py
k8s_datamodels/api/autoscaling/v1.py
k8s_datamodels/api/autoscaling/v2.py
k8s_datamodels/api/autoscaling/v2beta1.py
k8s_datamodels/api/autoscaling/v2beta2.py
k8s_datamodels/api/batch/__init__.py
k8s_datamodels/api/batch/v1.py
k8s_datamodels/api/batch/v1beta1.py
k8s_datamodels/api/certificates/__init__.py
k8s_datamodels/api/certificates/v1.py
k8s_datamodels/api/coordination/__init__.py
k8s_datamodels/api/coordination/v1.py
k8s_datamodels/api/core/__init__.py
k8s_datamodels/api/core/v1.py
k8s_datamodels/api/discovery/__init__.py
k8s_datamodels/api/discovery/v1.py
k8s_datamodels/api/discovery/v1beta1.py
k8s_datamodels/api/events/__init__.py
k8s_datamodels/api/events/v1.py
k8s_datamodels/api/events/v1beta1.py
k8s_datamodels/api/flowcontrol/__init__.py
k8s_datamodels/api/flowcontrol/v1beta1.py
k8s_datamodels/api/flowcontrol/v1beta2.py
k8s_datamodels/api/networking/__init__.py
k8s_datamodels/api/networking/v1.py
k8s_datamodels/api/node/__init__.py
k8s_datamodels/api/node/v1.py
k8s_datamodels/api/node/v1beta1.py
k8s_datamodels/api/policy/__init__.py
k8s_datamodels/api/policy/v1.py
k8s_datamodels/api/policy/v1beta1.py
k8s_datamodels/api/rbac/__init__.py
k8s_datamodels/api/rbac/v1.py
k8s_datamodels/api/scheduling/__init__.py
k8s_datamodels/api/scheduling/v1.py
k8s_datamodels/api/storage/__init__.py
k8s_datamodels/api/storage/v1.py
k8s_datamodels/api/storage/v1beta1.py
k8s_datamodels/apiextensions_apiserver/__init__.py
k8s_datamodels-1.24.3.post2.dist-info/METADATA
k8s_datamodels-1.24.3.post2.dist-info/WHEEL
k8s_datamodels-1.24.3.post2.dist-info/licenses/LICENSE
k8s_datamodels-1.24.3.post2.dist-info/RECORD
