Metadata-Version: 2.1
Name: k8s-datamodels
Version: 1.24.3.post2
Summary: Kubernetes specs Pydantic datamodels
Project-URL: Homepage, https://github.com/airspot-dev/k8s-datamodels
Author-email: "Alberto Degli Esposti @Airspot" <alberto@airspot.tech>
License: MIT License
Classifier: License :: OSI Approved :: MIT License
Classifier: Operating System :: OS Independent
Classifier: Programming Language :: Python :: 3
Requires-Python: >=3.7
